{"type":"FeatureCollection","crs":{"type":"name","properties":{"name":"EPSG:5186"}},"features":[{"type":"Feature","id":0,"geometry":{"type":"Point","coordinates":[186816.91578429256,350267.60228050547]},"properties":{"FID":0,"reclass":1}},{"type":"Feature","id":1,"geometry":{"type":"Point","coordinates":[186822.55369466296,350265.54948566435]},"properties":{"FID":1,"reclass":1}},{"type":"Feature","id":2,"geometry":{"type":"Point","coordinates":[186828.19160503306,350263.49669082311]},"properties":{"FID":2,"reclass":2}},{"type":"Feature","id":3,"geometry":{"type":"Point","coordinates":[186833.82951540261,350261.44389598252]},"properties":{"FID":3,"reclass":1}},{"type":"Feature","id":4,"geometry":{"type":"Point","coordinates":[186839.46742577371,350259.39110114047]},"properties":{"FID":4,"reclass":1}},{"type":"Feature","id":5,"geometry":{"type":"Point","coordinates":[186845.10533614227,350257.33830629988]},"properties":{"FID":5,"reclass":1}},{"type":"Feature","id":6,"geometry":{"type":"Point","coordinates":[186850.74324651199,350255.28551145771]},"properties":{"FID":6,"reclass":1}},{"type":"Feature","id":7,"geometry":{"type":"Point","coordinates":[186856.38115688361,350253.23271661816]},"properties":{"FID":7,"reclass":1}},{"type":"Feature","id":8,"geometry":{"type":"Point","coordinates":[186862.01906725345,350251.17992177623]},"properties":{"FID":8,"reclass":1}},{"type":"Feature","id":9,"geometry":{"type":"Point","coordinates":[186867.65697762198,350249.12712693342]},"properties":{"FID":9,"reclass":1}},{"type":"Feature","id":10,"geometry":{"type":"Point","coordinates":[186873.29488799346,350247.07433209324]},"properties":{"FID":10,"reclass":1}},{"type":"Feature","id":11,"geometry":{"type":"Point","coordinates":[186878.93279836333,350245.02153725206]},"properties":{"FID":11,"reclass":1}},{"type":"Feature","id":12,"geometry":{"type":"Point","coordinates":[186884.57070873404,350242.96874241147]},"properties":{"FID":12,"reclass":2}},{"type":"Feature","id":13,"geometry":{"type":"Point","coordinates":[186890.2086191038,350240.91594757105]},"properties":{"FID":13,"reclass":2}},{"type":"Feature","id":14,"geometry":{"type":"Point","coordinates":[186895.84652947201,350238.8631527283]},"properties":{"FID":14,"reclass":3}},{"type":"Feature","id":15,"geometry":{"type":"Point","coordinates":[186901.48443984118,350236.81035788759]},"properties":{"FID":15,"reclass":2}},{"type":"Feature","id":16,"geometry":{"type":"Point","coordinates":[186907.12235021344,350234.75756304729]},"properties":{"FID":16,"reclass":2}},{"type":"Feature","id":17,"geometry":{"type":"Point","coordinates":[186818.96857913485,350273.24019087694]},"properties":{"FID":17,"reclass":1}},{"type":"Feature","id":18,"geometry":{"type":"Point","coordinates":[186824.60648950387,350271.18739603442]},"properties":{"FID":18,"reclass":1}},{"type":"Feature","id":19,"geometry":{"type":"Point","coordinates":[186830.2443998745,350269.1346011936]},"properties":{"FID":19,"reclass":1}},{"type":"Feature","id":20,"geometry":{"type":"Point","coordinates":[186835.88231024434,350267.08180635126]},"properties":{"FID":20,"reclass":1}},{"type":"Feature","id":21,"geometry":{"type":"Point","coordinates":[186841.52022061343,350265.02901151031]},"properties":{"FID":21,"reclass":1}},{"type":"Feature","id":22,"geometry":{"type":"Point","coordinates":[186847.15813098522,350262.97621666937]},"properties":{"FID":22,"reclass":1}},{"type":"Feature","id":23,"geometry":{"type":"Point","coordinates":[186852.79604135492,350260.92342182773]},"properties":{"FID":23,"reclass":1}},{"type":"Feature","id":24,"geometry":{"type":"Point","coordinates":[186858.43395172516,350258.87062698707]},"properties":{"FID":24,"reclass":1}},{"type":"Feature","id":25,"geometry":{"type":"Point","coordinates":[186864.07186209547,350256.81783214578]},"properties":{"FID":25,"reclass":1}},{"type":"Feature","id":26,"geometry":{"type":"Point","coordinates":[186869.7097724643,350254.76503730402]},"properties":{"FID":26,"reclass":1}},{"type":"Feature","id":27,"geometry":{"type":"Point","coordinates":[186875.34768283315,350252.71224246343]},"properties":{"FID":27,"reclass":1}},{"type":"Feature","id":28,"geometry":{"type":"Point","coordinates":[186880.98559320479,350250.65944762318]},"properties":{"FID":28,"reclass":2}},{"type":"Feature","id":29,"geometry":{"type":"Point","coordinates":[186886.62350357429,350248.60665278236]},"properties":{"FID":29,"reclass":2}},{"type":"Feature","id":30,"geometry":{"type":"Point","coordinates":[186892.26141394387,350246.55385794037]},"properties":{"FID":30,"reclass":2}},{"type":"Feature","id":31,"geometry":{"type":"Point","coordinates":[186897.89932431461,350244.50106309896]},"properties":{"FID":31,"reclass":2}},{"type":"Feature","id":32,"geometry":{"type":"Point","coordinates":[186903.53723468329,350242.44826825778]},"properties":{"FID":32,"reclass":2}},{"type":"Feature","id":33,"geometry":{"type":"Point","coordinates":[186909.17514505421,350240.39547341637]},"properties":{"FID":33,"reclass":2}},{"type":"Feature","id":34,"geometry":{"type":"Point","coordinates":[186821.02137397401,350278.87810124527]},"properties":{"FID":34,"reclass":2}},{"type":"Feature","id":35,"geometry":{"type":"Point","coordinates":[186826.65928434543,350276.82530640438]},"properties":{"FID":35,"reclass":1}},{"type":"Feature","id":36,"geometry":{"type":"Point","coordinates":[186832.29719471591,350274.77251156257]},"properties":{"FID":36,"reclass":1}},{"type":"Feature","id":37,"geometry":{"type":"Point","coordinates":[186837.93510508697,350272.71971672244]},"properties":{"FID":37,"reclass":2}},{"type":"Feature","id":38,"geometry":{"type":"Point","coordinates":[186843.57301545638,350270.66692188091]},"properties":{"FID":38,"reclass":2}},{"type":"Feature","id":39,"geometry":{"type":"Point","coordinates":[186849.21092582465,350268.61412703904]},"properties":{"FID":39,"reclass":3}},{"type":"Feature","id":40,"geometry":{"type":"Point","coordinates":[186854.84883619563,350266.56133219833]},"properties":{"FID":40,"reclass":2}},{"type":"Feature","id":41,"geometry":{"type":"Point","coordinates":[186860.4867465655,350264.50853735721]},"properties":{"FID":41,"reclass":2}},{"type":"Feature","id":42,"geometry":{"type":"Point","coordinates":[186866.12465693563,350262.45574251626]},"properties":{"FID":42,"reclass":2}},{"type":"Feature","id":43,"geometry":{"type":"Point","coordinates":[186871.76256730489,350260.40294767526]},"properties":{"FID":43,"reclass":3}},{"type":"Feature","id":44,"geometry":{"type":"Point","coordinates":[186877.40047767543,350258.35015283397]},"properties":{"FID":44,"reclass":2}},{"type":"Feature","id":45,"geometry":{"type":"Point","coordinates":[186883.04654430333,350256.30276331119]},"properties":{"FID":45,"reclass":1}},{"type":"Feature","id":46,"geometry":{"type":"Point","coordinates":[186888.67629841648,350254.24456315191]},"properties":{"FID":46,"reclass":3}},{"type":"Feature","id":47,"geometry":{"type":"Point","coordinates":[186894.31420878507,350252.19176830904]},"properties":{"FID":47,"reclass":3}},{"type":"Feature","id":48,"geometry":{"type":"Point","coordinates":[186899.9521191541,350250.13897346886]},"properties":{"FID":48,"reclass":3}},{"type":"Feature","id":49,"geometry":{"type":"Point","coordinates":[186905.59002952668,350248.08617862809]},"properties":{"FID":49,"reclass":1}},{"type":"Feature","id":50,"geometry":{"type":"Point","coordinates":[186911.22793989675,350246.03338378703]},"properties":{"FID":50,"reclass":2}},{"type":"Feature","id":51,"geometry":{"type":"Point","coordinates":[186823.0741688151,350284.51601161587]},"properties":{"FID":51,"reclass":1}},{"type":"Feature","id":52,"geometry":{"type":"Point","coordinates":[186828.71207918465,350282.46321677347]},"properties":{"FID":52,"reclass":2}},{"type":"Feature","id":53,"geometry":{"type":"Point","coordinates":[186834.3499895561,350280.41042193293]},"properties":{"FID":53,"reclass":3}},{"type":"Feature","id":54,"geometry":{"type":"Point","coordinates":[186839.98789992725,350278.35762709193]},"properties":{"FID":54,"reclass":2}},{"type":"Feature","id":55,"geometry":{"type":"Point","coordinates":[186845.62581029948,350276.30483225256]},"properties":{"FID":55,"reclass":2}},{"type":"Feature","id":56,"geometry":{"type":"Point","coordinates":[186851.26372066778,350274.25203741033]},"properties":{"FID":56,"reclass":1}},{"type":"Feature","id":57,"geometry":{"type":"Point","coordinates":[186856.90163103596,350272.19924256898]},"properties":{"FID":57,"reclass":2}},{"type":"Feature","id":58,"geometry":{"type":"Point","coordinates":[186862.53954140667,350270.14644772705]},"properties":{"FID":58,"reclass":1}},{"type":"Feature","id":59,"geometry":{"type":"Point","coordinates":[186868.17745177608,350268.0936528857]},"properties":{"FID":59,"reclass":2}},{"type":"Feature","id":60,"geometry":{"type":"Point","coordinates":[186873.81536214537,350266.04085804452]},"properties":{"FID":60,"reclass":2}},{"type":"Feature","id":61,"geometry":{"type":"Point","coordinates":[186879.45327251623,350263.98806320369]},"properties":{"FID":61,"reclass":1}},{"type":"Feature","id":62,"geometry":{"type":"Point","coordinates":[186885.091182887,350261.93526836252]},"properties":{"FID":62,"reclass":1}},{"type":"Feature","id":63,"geometry":{"type":"Point","coordinates":[186890.72909325731,350259.88247352064]},"properties":{"FID":63,"reclass":2}},{"type":"Feature","id":64,"geometry":{"type":"Point","coordinates":[186896.36700362668,350257.82967868034]},"properties":{"FID":64,"reclass":3}},{"type":"Feature","id":65,"geometry":{"type":"Point","coordinates":[186902.00491399589,350255.77688383881]},"properties":{"FID":65,"reclass":3}},{"type":"Feature","id":66,"geometry":{"type":"Point","coordinates":[186907.64282436651,350253.7240889977]},"properties":{"FID":66,"reclass":1}},{"type":"Feature","id":67,"geometry":{"type":"Point","coordinates":[186913.28073473703,350251.67129415681]},"properties":{"FID":67,"reclass":2}},{"type":"Feature","id":68,"geometry":{"type":"Point","coordinates":[186825.12696365814,350290.15392198565]},"properties":{"FID":68,"reclass":1}},{"type":"Feature","id":69,"geometry":{"type":"Point","coordinates":[186830.7648740283,350288.10112714412]},"properties":{"FID":69,"reclass":3}},{"type":"Feature","id":70,"geometry":{"type":"Point","coordinates":[186836.40278439721,350286.04833230277]},"properties":{"FID":70,"reclass":3}},{"type":"Feature","id":71,"geometry":{"type":"Point","coordinates":[186842.04069476685,350283.99553746235]},"properties":{"FID":71,"reclass":2}},{"type":"Feature","id":72,"geometry":{"type":"Point","coordinates":[186847.67860513774,350281.94274262013]},"properties":{"FID":72,"reclass":2}},{"type":"Feature","id":73,"geometry":{"type":"Point","coordinates":[186853.31651550776,350279.88994777959]},"properties":{"FID":73,"reclass":1}},{"type":"Feature","id":74,"geometry":{"type":"Point","coordinates":[186858.95442587728,350277.83715293894]},"properties":{"FID":74,"reclass":2}},{"type":"Feature","id":75,"geometry":{"type":"Point","coordinates":[186864.59233624773,350275.7843580973]},"properties":{"FID":75,"reclass":3}},{"type":"Feature","id":76,"geometry":{"type":"Point","coordinates":[186870.23024661883,350273.73156325571]},"properties":{"FID":76,"reclass":3}},{"type":"Feature","id":77,"geometry":{"type":"Point","coordinates":[186875.86815698716,350271.67876841425]},"properties":{"FID":77,"reclass":3}},{"type":"Feature","id":78,"geometry":{"type":"Point","coordinates":[186881.50606735639,350269.62597357319]},"properties":{"FID":78,"reclass":2}},{"type":"Feature","id":79,"geometry":{"type":"Point","coordinates":[186887.14397772867,350267.5731787323]},"properties":{"FID":79,"reclass":3}},{"type":"Feature","id":80,"geometry":{"type":"Point","coordinates":[186892.78188809799,350265.52038389136]},"properties":{"FID":80,"reclass":3}},{"type":"Feature","id":81,"geometry":{"type":"Point","coordinates":[186898.41979846678,350263.4675890503]},"properties":{"FID":81,"reclass":3}},{"type":"Feature","id":82,"geometry":{"type":"Point","coordinates":[186904.05770883709,350261.41479420889]},"properties":{"FID":82,"reclass":3}},{"type":"Feature","id":83,"geometry":{"type":"Point","coordinates":[186909.69561920722,350259.36199936771]},"properties":{"FID":83,"reclass":2}},{"type":"Feature","id":84,"geometry":{"type":"Point","coordinates":[186915.3335295773,350257.30920452636]},"properties":{"FID":84,"reclass":2}},{"type":"Feature","id":85,"geometry":{"type":"Point","coordinates":[186827.17975849766,350295.79183235398]},"properties":{"FID":85,"reclass":3}},{"type":"Feature","id":86,"geometry":{"type":"Point","coordinates":[186832.81766886887,350293.73903751437]},"properties":{"FID":86,"reclass":3}},{"type":"Feature","id":87,"geometry":{"type":"Point","coordinates":[186838.45557923859,350291.68624267355]},"properties":{"FID":87,"reclass":3}},{"type":"Feature","id":88,"geometry":{"type":"Point","coordinates":[186844.09348960771,350289.63344783161]},"properties":{"FID":88,"reclass":3}},{"type":"Feature","id":89,"geometry":{"type":"Point","coordinates":[186849.73139997921,350287.58065299067]},"properties":{"FID":89,"reclass":3}},{"type":"Feature","id":90,"geometry":{"type":"Point","coordinates":[186855.369310348,350285.52785814938]},"properties":{"FID":90,"reclass":3}},{"type":"Feature","id":91,"geometry":{"type":"Point","coordinates":[186861.00722071718,350283.47506330878]},"properties":{"FID":91,"reclass":3}},{"type":"Feature","id":92,"geometry":{"type":"Point","coordinates":[186866.64513108894,350281.42226846732]},"properties":{"FID":92,"reclass":2}},{"type":"Feature","id":93,"geometry":{"type":"Point","coordinates":[186872.28304146024,350279.36947362532]},"properties":{"FID":93,"reclass":3}},{"type":"Feature","id":94,"geometry":{"type":"Point","coordinates":[186877.92095183025,350277.3166787849]},"properties":{"FID":94,"reclass":3}},{"type":"Feature","id":95,"geometry":{"type":"Point","coordinates":[186883.55886219777,350275.26388394361]},"properties":{"FID":95,"reclass":3}},{"type":"Feature","id":96,"geometry":{"type":"Point","coordinates":[186889.19677256845,350273.21108910255]},"properties":{"FID":96,"reclass":3}},{"type":"Feature","id":97,"geometry":{"type":"Point","coordinates":[186894.83468293998,350271.15829426266]},"properties":{"FID":97,"reclass":2}},{"type":"Feature","id":98,"geometry":{"type":"Point","coordinates":[186900.4725933086,350269.10549942125]},"properties":{"FID":98,"reclass":3}},{"type":"Feature","id":99,"geometry":{"type":"Point","coordinates":[186906.11050367716,350267.05270457873]},"properties":{"FID":99,"reclass":3}},{"type":"Feature","id":100,"geometry":{"type":"Point","coordinates":[186911.74841404698,350264.99990973796]},"properties":{"FID":100,"reclass":3}},{"type":"Feature","id":101,"geometry":{"type":"Point","coordinates":[186917.38632441708,350262.94711489731]},"properties":{"FID":101,"reclass":3}}]}